pitch_squeezer.py
pitchsqueezer-0.1.0.dist-info/LICENSE
pitchsqueezer-0.1.0.dist-info/METADATA
pitchsqueezer-0.1.0.dist-info/WHEEL
pitchsqueezer-0.1.0.dist-info/entry_points.txt
pitchsqueezer-0.1.0.dist-info/top_level.txt
pitchsqueezer-0.1.0.dist-info/RECORD
