Metadata-Version: 2.1
Name: pitchsqueezer
Version: 0.1.0
Summary: Robust pitch tracker for speech, using synchrosqueezing and spectral autocorrelation
Author-email: Antti Suni <antti.suni@helsinki.fi>
Maintainer-email: Antti Suni <antti.suni@helsinki.fi>
Project-URL: Homepage, https://github.com/asuni/PitchSqueezer
Project-URL: Bug Reports, https://github.com/asuni/PitchSqueezer/issues
Project-URL: Funding, https://donate.pypi.org
Project-URL: Source, https://github.com/asuni/PitchSqueezer
Keywords: speech analysis,pitch,prosody,tts
Classifier: Development Status :: 3 - Alpha
Classifier: Intended Audience :: Science/Research
Classifier: Topic :: Software Development :: Build Tools
Classifier: License :: OSI Approved :: GNU General Public License v3 (GPLv3)
Classifier: Programming Language :: Python :: 3
Classifier: Programming Language :: Python :: 3.7
Classifier: Programming Language :: Python :: 3.8
Classifier: Programming Language :: Python :: 3.9
Classifier: Programming Language :: Python :: 3.10
Classifier: Programming Language :: Python :: 3.11
Classifier: Programming Language :: Python :: 3 :: Only
Requires-Python: >=3.7
License-File: LICENSE
Requires-Dist: numpy
Requires-Dist: scipy
Requires-Dist: joblib
Requires-Dist: librosa
Requires-Dist: ssqueezepy
Requires-Dist: tqdm
Requires-Dist: matplotlib
